avro_gen_topkrabbensteam-0.0.2.dist-info/METADATA
avro_gen_topkrabbensteam-0.0.2.dist-info/RECORD
avro_gen_topkrabbensteam-0.0.2.dist-info/WHEEL
avro_gen_topkrabbensteam-0.0.2.dist-info/top_level.txt
avrogen/__init__.py
avrogen/avrojson.py
avrogen/core_writer.py
avrogen/dict_wrapper.py
avrogen/logical.py
avrogen/namespace.py
avrogen/protocol.py
avrogen/protocol_writer.py
avrogen/schema.py
avrogen/tabbed_writer.py
